osbparser/__init__.py
osbparser/enums.py
osbparser/exception.py
osbparser/interpolator.py
osbparser/logger.py
osbparser/osb.py
osbparser/tree.py
osbparser/utils.py
osbparser-0.1.0.dist-info/LICENSE
osbparser-0.1.0.dist-info/WHEEL
osbparser-0.1.0.dist-info/METADATA
osbparser-0.1.0.dist-info/RECORD
